ohmyxdu/__init__.py
ohmyxdu/auth/__init__.py
ohmyxdu/auth/ids.py
ohmyxdu/auth/wx.py
ohmyxdu/auth/zfw.py
ohmyxdu/builtins/credentials.py
ohmyxdu/builtins/show.py
ohmyxdu/builtins/version.py
ohmyxdu/console.py
ohmyxdu/globals.py
ohmyxdu/plugins/export_class_schedule.py
ohmyxdu/plugins/get_borrowed_books.py
ohmyxdu/plugins/get_card_balance.py
ohmyxdu/plugins/get_grade.py
ohmyxdu/plugins/get_network_usage.py
ohmyxdu/security/__init__.py
ohmyxdu/utils/__init__.py
ohmyxdu/utils/data_structure.py
ohmyxdu/utils/icalendar_helper.py
oh_my_xdu-0.1.4.dist-info/entry_points.txt
oh_my_xdu-0.1.4.dist-info/LICENSE
oh_my_xdu-0.1.4.dist-info/WHEEL
oh_my_xdu-0.1.4.dist-info/METADATA
oh_my_xdu-0.1.4.dist-info/RECORD
