Metadata-Version: 2.1
Name: oh-my-xdu
Version: 0.1.4
Summary: Useful tools for XDU students
License: LGPL-3.0-or-later
Author: zkonge
Author-email: zkonge@outlook.com
Requires-Python: >=3.7,<4.0
Classifier: License :: OSI Approved :: GNU Lesser General Public License v3 or later (LGPLv3+)
Classifier: Programming Language :: Python :: 3
Classifier: Programming Language :: Python :: 3.7
Classifier: Programming Language :: Python :: 3.8
Classifier: Programming Language :: Python :: 3.9
Requires-Dist: defopt (>=6.0,<7.0)
Requires-Dist: icalendar (>=4.0.6,<5.0.0)
Requires-Dist: loguru (>=0.5.1,<0.6.0)
Requires-Dist: parsel (>=1.6.0,<2.0.0)
Requires-Dist: pycryptodome (>=3.9.8,<4.0.0)
Requires-Dist: requests (>=2.24.0,<3.0.0)
Requires-Dist: toml (>=0.10.1,<0.11.0)
